odoo/addons/account_payment_sepa_base/README.rst
odoo/addons/account_payment_sepa_base/__init__.py
odoo/addons/account_payment_sepa_base/__manifest__.py
odoo/addons/account_payment_sepa_base/post_install.py
odoo/addons/account_payment_sepa_base/i18n/account_banking_pain_base.pot
odoo/addons/account_payment_sepa_base/i18n/account_payment_sepa_base.pot
odoo/addons/account_payment_sepa_base/i18n/ca.po
odoo/addons/account_payment_sepa_base/i18n/de.po
odoo/addons/account_payment_sepa_base/i18n/es.po
odoo/addons/account_payment_sepa_base/i18n/es_AR.po
odoo/addons/account_payment_sepa_base/i18n/fr.po
odoo/addons/account_payment_sepa_base/i18n/hr.po
odoo/addons/account_payment_sepa_base/i18n/it.po
odoo/addons/account_payment_sepa_base/i18n/nb_NO.po
odoo/addons/account_payment_sepa_base/i18n/nl.po
odoo/addons/account_payment_sepa_base/i18n/pt_BR.po
odoo/addons/account_payment_sepa_base/i18n/sl.po
odoo/addons/account_payment_sepa_base/i18n/sv.po
odoo/addons/account_payment_sepa_base/models/__init__.py
odoo/addons/account_payment_sepa_base/models/account_pain_regulatory_reporting.py
odoo/addons/account_payment_sepa_base/models/account_payment.py
odoo/addons/account_payment_sepa_base/models/account_payment_line.py
odoo/addons/account_payment_sepa_base/models/account_payment_lot.py
odoo/addons/account_payment_sepa_base/models/account_payment_method.py
odoo/addons/account_payment_sepa_base/models/account_payment_method_line.py
odoo/addons/account_payment_sepa_base/models/account_payment_order.py
odoo/addons/account_payment_sepa_base/models/res_company.py
odoo/addons/account_payment_sepa_base/models/res_currency.py
odoo/addons/account_payment_sepa_base/models/res_partner.py
odoo/addons/account_payment_sepa_base/models/res_partner_bank.py
odoo/addons/account_payment_sepa_base/readme/CONFIGURE.md
odoo/addons/account_payment_sepa_base/readme/CONTRIBUTORS.md
odoo/addons/account_payment_sepa_base/readme/DESCRIPTION.md
odoo/addons/account_payment_sepa_base/readme/INSTALL.md
odoo_addon_account_payment_sepa_base-19.0.1.0.0.3.dist-info/METADATA
odoo_addon_account_payment_sepa_base-19.0.1.0.0.3.dist-info/WHEEL
odoo_addon_account_payment_sepa_base-19.0.1.0.0.3.dist-info/top_level.txt
odoo_addon_account_payment_sepa_base-19.0.1.0.0.3.dist-info/RECORD
