Metadata-Version: 2.1
Name: odoo-addon-account_payment_sepa_base
Version: 19.0.1.0.0.3
Requires-Dist: lxml
Requires-Dist: odoo-addon-account_payment_batch_oca==19.0.*
Requires-Dist: odoo==19.0.*
Requires-Dist: unidecode
Summary: Base module for SEPA file generation
Home-page: https://github.com/OCA/bank-payment-alternative
License: AGPL-3
Author: Akretion, Noviat, Tecnativa, Odoo Community Association (OCA)
Author-email: support@odoo-community.org
Classifier: Programming Language :: Python
Classifier: Framework :: Odoo
Classifier: Framework :: Odoo :: 19.0
Classifier: License :: OSI Approved :: GNU Affero General Public License v3
